kx_python_flutter_bridge/__init__.py
kx_python_flutter_bridge/__version__.py
kx_python_flutter_bridge/jsonrpc_bridge.py
kx_python_flutter_bridge/jsonrpc/__init__.py
kx_python_flutter_bridge/jsonrpc/function_registry.py
kx_python_flutter_bridge/jsonrpc/protocol.py
kx_python_flutter_bridge/jsonrpc/server.py
kx_python_flutter_bridge-0.1.0.dist-info/licenses/LICENSE
kx_python_flutter_bridge-0.1.0.dist-info/METADATA
kx_python_flutter_bridge-0.1.0.dist-info/WHEEL
kx_python_flutter_bridge-0.1.0.dist-info/entry_points.txt
kx_python_flutter_bridge-0.1.0.dist-info/top_level.txt
kx_python_flutter_bridge-0.1.0.dist-info/RECORD
